mpi4all/__init__.py
mpi4all/baseBuilder.py
mpi4all/gobuilder.py
mpi4all/javabuilder.py
mpi4all/main.py
mpi4all/mpiparser.py
mpi4all/version.py
mpi4all-1.1.1.dev2.dist-info/LICENSE
mpi4all-1.1.1.dev2.dist-info/METADATA
mpi4all-1.1.1.dev2.dist-info/WHEEL
mpi4all-1.1.1.dev2.dist-info/entry_points.txt
mpi4all-1.1.1.dev2.dist-info/RECORD
