Metadata-Version: 2.1
Name: mpi4all
Version: 1.1.1.dev2
Summary: MPI4All: An MPI Binding Generator
Home-page: https://github.com/citiususc/mpi4all
License: LGPL-3.0-only
Keywords: HPC,MPI,Multi-language,Programming models
Author: César Pomar
Author-email: cesaralfredo.pineiro@usc.es
Requires-Python: >=3.9,<4.0
Classifier: License :: OSI Approved :: GNU Lesser General Public License v3 (LGPLv3)
Classifier: Programming Language :: Python :: 3
Classifier: Programming Language :: Python :: 3.9
Classifier: Programming Language :: Python :: 3.10
Classifier: Programming Language :: Python :: 3.11
Classifier: Programming Language :: Python :: 3.12
Classifier: Topic :: Software Development
Classifier: Topic :: Utilities
Project-URL: Repository, https://github.com/citiususc/mpi4all
